stc_tools/cli.py
stc_tools/client.py
stc_tools-1.2.2.dist-info/METADATA
stc_tools-1.2.2.dist-info/WHEEL
stc_tools-1.2.2.dist-info/entry_points.txt
stc_tools-1.2.2.dist-info/top_level.txt
stc_tools-1.2.2.dist-info/RECORD
